Metadata-Version: 2.1
Name: vtrans
Version: 3.5.0
Summary: This is a cross-platfrom self-updating translator for free and unlimited usage with upto 130 langauges
Home-page: https://github.com/megalosVigneswaran/vtrans/tree/main/vtrans
Author: S.Vigneswaran
Author-email: t896242@gmail.com
License: MIT
Keywords: translator,googletranslate,self-updating,googletrans,vtrans
Classifier: Development Status :: 5 - Production/Stable
Classifier: Intended Audience :: Education
Classifier: Intended Audience :: End Users/Desktop
Classifier: License :: Freeware
Classifier: Topic :: Education
Classifier: Operating System :: Microsoft :: Windows :: Windows 10
Classifier: Operating System :: Microsoft :: Windows :: Windows 8.1
Classifier: Operating System :: Microsoft :: Windows :: Windows 8
Classifier: License :: OSI Approved :: MIT License
Classifier: Programming Language :: Python
Classifier: Programming Language :: Python :: 3.8
